{
  "schemaVersion": 2,
  "app": {
    "name": "The Cube",
    "packageName": "com.thecube",
    "environment": "production",
    "configEnabled": true,
    "maintenanceMode": false,
    "maintenanceMessage": "The Cube is temporarily under maintenance. Please try again later.",
    "blockUnauthorizedBuilds": true,
    "allowedSigningCertificateSha256": [
      "a6b1bfe7efcbe01218f9e32939dde6247ff7cea9f7fb9cb338219c2d15d28eb1"
    ],
    "blockedVersionCodes": [],
    "blockedMessage": "This version of The Cube is no longer supported. Please install the official version."
  },
  "update": {
    "enabled": true,
    "checkOnLaunch": true,
    "checkIntervalHours": 1,
    "latestVersionCode": 20041,
    "minimumSupportedVersionCode": 20028,
    "latestVersionName": "2.0.41",
    "forceUpdate": true,
    "title": "The Cube 2.0.41 is ready",
    "message": "Install the latest version for stronger playback recovery, better episode matching, cleaner server choices, and smoother stream startup.",
    "releaseNotes": [
      "Improved main playback matching for TV episodes that previously returned empty results",
      "Added another main playback route to reduce load and improve fallback coverage",
      "Improved stream headers used by protected playback links",
      "Improved server quality labels and ordering",
      "Improved recovery when a returned stream is expired or unavailable",
      "Kept the original splash animation clean",
      "Fixed phone Manage Profiles opening the wrong screen",
      "Improved TV profile, banner, and focus stability",
      "Improved player loading and error actions on TV",
      "Cleaned quota warning text so raw JSON is never shown",
      "Replaced hardcoded version text with the installed app version"
    ],
    "platforms": {
      "androidPhone": {
        "enabled": true,
        "apkUrl": "https://github.com/cybruGhost/cube/releases/download/v2.0.41/app-release.apk",
        "fallbackUrl": "https://thecub.netlify.app",
        "sha256": "08e99125a954600b346ca7041aa36cb7427ebf194a26cfe492aaa4861dc09a09"
      },
      "androidTv": {
        "enabled": true,
        "apkUrl": "https://github.com/cybruGhost/cube/releases/download/v2.0.41/app-release.apk",
        "fallbackUrl": "https://thecub.netlify.app",
        "sha256": "08e99125a954600b346ca7041aa36cb7427ebf194a26cfe492aaa4861dc09a09"
      }
    }
  },
  "notifications": {
    "enabled": true,
    "showOnLaunch": true,
    "items": [
      {
        "id": "news-v2-0-41",
        "type": "news",
        "enabled": true,
        "title": "The Cube 2.0.41",
        "message": "Playback matching, recovery, phone profile management, and TV stability were improved.",
        "imageUrl": null,
        "actionLabel": "Open The Cube",
        "actionUrl": "https://thecub.netlify.app",
        "dismissible": true,
        "showOnce": true,
        "priority": 10
      },
      {
        "id": "support-development",
        "type": "support",
        "enabled": false,
        "title": "Support The Cube",
        "message": "Support is optional and helps development. Third-party servers may still go down or return errors.",
        "imageUrl": null,
        "actionLabel": "Support",
        "actionUrl": "https://support-pal-global.lovable.app/",
        "dismissible": true,
        "showOnce": true,
        "priority": 5
      }
    ]
  },
  "features": {
    "profiles": true,
    "kidsMode": true,
    "continueWatching": true,
    "watchLater": true,
    "playlists": true,
    "phoneDownloads": true,
    "tvDownloads": false,
    "castPlayer": false,
    "trailers": true,
    "externalPlayers": false
  },
  "ads": {
    "enabled": true,
    "provider": "admob",
    "showBanner": true,
    "showInterstitial": false,
    "android": {
      "appId": "ca-app-pub-7167154680086124~1956582131",
      "bannerAdUnitId": "ca-app-pub-7167154680086124/6551931099"
    }
  }
}
