{
  "schemaVersion": 2,
  "app": {
    "name": "The Cube",
    "packageName": "com.thecube",
    "environment": "production",
    "configEnabled": true,
    "maintenanceMode": false,
    "maintenanceMessage": "The Cube is temporarily under maintenance. Please try again later.",
    "blockUnauthorizedBuilds": true,
    "allowedSigningCertificateSha256": [
      "a6b1bfe7efcbe01218f9e32939dde6247ff7cea9f7fb9cb338219c2d15d28eb1"
    ],
    "blockedVersionCodes": [],
    "blockedMessage": "This version of The Cube is no longer supported. Please install the official version."
  },
  "update": {
    "enabled": true,
    "checkOnLaunch": true,
    "checkIntervalHours": 1,
    "latestVersionCode": 20062,
    "minimumSupportedVersionCode": 20028,
    "latestVersionName": "2.0.62",
    "forceUpdate": true,
    "title": "The Cube 2.0.62 is ready",
    "message": "Install the latest version for better playback ordering, steadier seeking, and cleaner embedded playback.",
    "releaseNotes": [
      "The first server choices are now ordered around the most reliable direct playback paths",
      "The selector avoids duplicate-looking file labels and keeps lower priority fallbacks later",
      "Wrong-title responses and video placeholder links are filtered before they reach the player",
      "Seeking on TV no longer switches servers just because playback is buffering after a seek",
      "Embedded playback has a darker full-surface load state and safer popup handling",
      "HLS and direct-file headers were tightened for more consistent playback",
      "Public update text no longer exposes internal provider details"
    ],
    "platforms": {
      "androidPhone": {
        "enabled": true,
        "apkUrl": "https://github.com/cybruGhost/cube/releases/download/v2.0.62/app-release.apk",
        "fallbackUrl": "https://github.com/cybruGhost/cube/releases/download/v2.0.62/app-release.apk",
        "sha256": "97fe93e36aaf580278d0f6778baf99a43595177ada909f00eb7b7132b79207fc"
      },
      "androidTv": {
        "enabled": true,
        "apkUrl": "https://github.com/cybruGhost/cube/releases/download/v2.0.62/app-release.apk",
        "fallbackUrl": "https://github.com/cybruGhost/cube/releases/download/v2.0.62/app-release.apk",
        "sha256": "97fe93e36aaf580278d0f6778baf99a43595177ada909f00eb7b7132b79207fc"
      }
    }
  },
  "notifications": {
    "enabled": true,
    "showOnLaunch": true,
    "items": [
      {
        "id": "news-v2-0-62",
        "type": "news",
        "enabled": false,
        "title": "The Cube 2.0.62",
        "message": "Playback ordering, seeking, and embedded playback were improved.",
        "imageUrl": null,
        "actionLabel": "Open The Cube",
        "actionUrl": "https://thecub.netlify.app",
        "dismissible": true,
        "showOnce": true,
        "priority": 10
      },
         {
      "id": "active-development-notice-v2-0-62",
      "type": "notice",
      "enabled": true,
      "title": "Development Update",
      "message": "Hi everyone! 👋 Development officially started on July 10, and work is now actively in progress. It’s going to be a big week as we focus on smoother playback, better streaming performance, improved stability, and fixing the issues you’ve reported. Downloads are also being improved while the main playback work continues. Thank you for your patience, support, and for sticking with THE CUBE. More updates are on the way. ❤️",
      "imageUrl": "https://qvcuxlmdkrdumkmgdzui.supabase.co/storage/v1/object/public/notification-images/noti_1783766152192.png",
      "actionLabel": "Donate",
      "actionUrl": "https://cyberghost-shop.fourthwall.com",
      "dismissible": true,
      "showOnce": false,
      "priority": 20
    },
      {
        "id": "support-development",
        "type": "support",
        "enabled": true,
        "title": "Support The Cube",
        "message": "Support is optional and helps development. Third-party servers may still go down or return errors.",
        "imageUrl": "https://qvcuxlmdkrdumkmgdzui.supabase.co/storage/v1/object/public/notification-images/noti_1782737631424.png",
        "actionLabel": "Support",
        "actionUrl": "https://support-pal-global.lovable.app/",
        "dismissible": true,
        "showOnce": true,
        "priority": 5
      }
    ]
  },
  "features": {
    "profiles": true,
    "kidsMode": true,
    "continueWatching": true,
    "watchLater": true,
    "playlists": true,
    "phoneDownloads": true,
    "tvDownloads": false,
    "castPlayer": false,
    "trailers": true,
    "externalPlayers": false
  },
  "ads": {
    "enabled": true,
    "provider": "admob",
    "showBanner": true,
    "showInterstitial": false,
    "android": {
      "appId": "ca-app-pub-7167154680086124~1956582131",
      "bannerAdUnitId": "ca-app-pub-7167154680086124/6551931099"
    }
  }
}
